[
  {
    "name": "Siti Marlina",
    "school": "Tutor Privat, Bandung",
    "quote": "Sejak ikut pertemuan bulanan Tera, saya jadi lebih paham cara mendekati siswa yang sulit fokus. Ternyata bukan mereka yang bermasalah, tapi cara saya menyampaikan yang perlu berubah.",
    "photo": ""
  },
  {
    "name": "Andi Prasetyo",
    "school": "Guru SMP, Yogyakarta",
    "quote": "Awalnya saya ikut Tera cuma buat cari info lowongan mengajar. Tapi yang paling berharga justru cerita-cerita dari guru lain yang bikin saya nggak merasa sendirian.",
    "photo": ""
  }
]
